[
    {
        "countryCode": "UA",
        "adLogo": "https://i.imgur.com/hClDDjm.png",
        "adImg": "https://i.imgur.com/pjL1Pnw.jpg",
        "adVideo": "",
        "adAction": "Открыть",
        "adTitle": "Monobank. Мобильный банк без отделений",
        "adDescription": "Мы не несем траты на содержание отделений. Поэтому мы предлагаем самые выгодные тарифы",
        "adRating": 5,
        "adLink": "https://ad.admitad.com/g/yfp1lg37f6df1db38a4766f30a08a3/"
    },
    {
        "countryCode": "ID",
        "adLogo": "https://i.imgur.com/1XPFEio.png",
        "adImg": "https://i.imgur.com/4SRzJRP.png",
        "adVideo": "",
        "adAction": "Install",
        "adTitle": "UC Browser - The fastest browser",
        "adDescription": "Web browser for Android with built-in adaptive content, fast download function, save traffic.",
        "adRating": 5,
        "adLink": "http://shakesmobi.com/LUOS/sub1/sub2/sub3/sub4/sub5"
    },
    {
        "countryCode": "VN",
        "adLogo": "https://i.imgur.com/1XPFEio.png",
        "adImg": "https://i.imgur.com/4SRzJRP.png",
        "adVideo": "",
        "adAction": "Install",
        "adTitle": "UC Browser - The fastest browser",
        "adDescription": "Web browser for Android with built-in adaptive content, fast download function, save traffic.",
        "adRating": 5,
        "adLink": "http://shakesmobi.com/LUOS/sub1/sub2/sub3/sub4/sub5"
    },{
        "countryCode": "IN",
        "adLogo": "https://i.imgur.com/1XPFEio.png",
        "adImg": "https://i.imgur.com/4SRzJRP.png",
        "adVideo": "",
        "adAction": "Install",
        "adTitle": "UC Browser - The fastest browser",
        "adDescription": "Web browser for Android with built-in adaptive content, fast download function, save traffic.",
        "adRating": 5,
        "adLink": "http://shakesmobi.com/LUOS/sub1/sub2/sub3/sub4/sub5"
    },
    {
        "countryCode": "MY",
        "adLogo": "https://i.imgur.com/1XPFEio.png",
        "adImg": "https://i.imgur.com/4SRzJRP.png",
        "adVideo": "",
        "adAction": "Install",
        "adTitle": "UC Browser - The fastest browser",
        "adDescription": "Web browser for Android with built-in adaptive content, fast download function, save traffic.",
        "adRating": 5,
        "adLink": "http://shakesmobi.com/LUOS/sub1/sub2/sub3/sub4/sub5"
    },
    {
        "countryCode": "TH",
        "adLogo": "https://i.imgur.com/hiWd5Nz.png",
        "adImg": "https://i.imgur.com/595EqAj.jpg",
        "adVideo": "",
        "adAction": "Install",
        "adTitle": "AliExpress is a trading platform in your hands",
        "adDescription": "Millions of users find here the desired products from China at the best prices",
        "adRating": 5,
        "adLink": "http://shakesmobi.com/QUOS/sub1/sub2/sub3/sub4/sub5"
    },
    {
        "countryCode": "KW",
        "adLogo": "https://i.imgur.com/hiWd5Nz.png",
        "adImg": "https://i.imgur.com/595EqAj.jpg",
        "adVideo": "",
        "adAction": "Install",
        "adTitle": "AliExpress is a trading platform in your hands",
        "adDescription": "Millions of users find here the desired products from China at the best prices",
        "adRating": 5,
        "adLink": "http://shakesmobi.com/QUOS/sub1/sub2/sub3/sub4/sub5"
    },
    {
        "countryCode": "QA",
        "adLogo": "https://i.imgur.com/hiWd5Nz.png",
        "adImg": "https://i.imgur.com/595EqAj.jpg",
        "adVideo": "",
        "adAction": "Install",
        "adTitle": "AliExpress is a trading platform in your hands",
        "adDescription": "Millions of users find here the desired products from China at the best prices",
        "adRating": 5,
        "adLink": "http://shakesmobi.com/QUOS/sub1/sub2/sub3/sub4/sub5"
    },
    {
        "countryCode": "AE",
        "adLogo": "https://i.imgur.com/hiWd5Nz.png",
        "adImg": "https://i.imgur.com/595EqAj.jpg",
        "adVideo": "",
        "adAction": "Install",
        "adTitle": "AliExpress is a trading platform in your hands",
        "adDescription": "Millions of users find here the desired products from China at the best prices",
        "adRating": 5,
        "adLink": "http://shakesmobi.com/QUOS/sub1/sub2/sub3/sub4/sub5"
    },
    {
        "countryCode": "IQ",
        "adLogo": "https://i.imgur.com/hiWd5Nz.png",
        "adImg": "https://i.imgur.com/595EqAj.jpg",
        "adVideo": "",
        "adAction": "Install",
        "adTitle": "AliExpress is a trading platform in your hands",
        "adDescription": "Millions of users find here the desired products from China at the best prices",
        "adRating": 5,
        "adLink": "http://shakesmobi.com/QUOS/sub1/sub2/sub3/sub4/sub5"
    },
    {
        "countryCode": "CL",
        "adLogo": "https://i.imgur.com/hiWd5Nz.png",
        "adImg": "https://i.imgur.com/595EqAj.jpg",
        "adVideo": "",
        "adAction": "Install",
        "adTitle": "AliExpress is a trading platform in your hands",
        "adDescription": "Millions of users find here the desired products from China at the best prices",
        "adRating": 5,
        "adLink": "http://shakesmobi.com/QUOS/sub1/sub2/sub3/sub4/sub5"
    },
    {
        "countryCode": "KR",
        "adLogo": "https://i.imgur.com/hiWd5Nz.png",
        "adImg": "https://i.imgur.com/595EqAj.jpg",
        "adVideo": "",
        "adAction": "Install",
        "adTitle": "AliExpress is a trading platform in your hands",
        "adDescription": "Millions of users find here the desired products from China at the best prices",
        "adRating": 5,
        "adLink": "http://shakesmobi.com/QUOS/sub1/sub2/sub3/sub4/sub5"
    },
    {
        "countryCode": "IL",
        "adLogo": "https://i.imgur.com/hiWd5Nz.png",
        "adImg": "https://i.imgur.com/595EqAj.jpg",
        "adVideo": "",
        "adAction": "Install",
        "adTitle": "AliExpress is a trading platform in your hands",
        "adDescription": "Millions of users find here the desired products from China at the best prices",
        "adRating": 5,
        "adLink": "http://shakesmobi.com/QUOS/sub1/sub2/sub3/sub4/sub5"
    },{
        "countryCode": "MX",
        "adLogo": "https://i.imgur.com/hiWd5Nz.png",
        "adImg": "https://i.imgur.com/595EqAj.jpg",
        "adVideo": "",
        "adAction": "Install",
        "adTitle": "AliExpress is a trading platform in your hands",
        "adDescription": "Millions of users find here the desired products from China at the best prices",
        "adRating": 5,
        "adLink": "http://shakesmobi.com/QUOS/sub1/sub2/sub3/sub4/sub5"
    },{
        "countryCode": "ID",
        "adLogo": "https://i.imgur.com/hiWd5Nz.png",
        "adImg": "https://i.imgur.com/595EqAj.jpg",
        "adVideo": "",
        "adAction": "Install",
        "adTitle": "AliExpress is a trading platform in your hands",
        "adDescription": "Millions of users find here the desired products from China at the best prices",
        "adRating": 5,
        "adLink": "http://shakesmobi.com/QUOS/sub1/sub2/sub3/sub4/sub5"
    },{
        "countryCode": "MY",
        "adLogo": "https://i.imgur.com/hiWd5Nz.png",
        "adImg": "https://i.imgur.com/595EqAj.jpg",
        "adVideo": "",
        "adAction": "Install",
        "adTitle": "AliExpress is a trading platform in your hands",
        "adDescription": "Millions of users find here the desired products from China at the best prices",
        "adRating": 5,
        "adLink": "http://shakesmobi.com/QUOS/sub1/sub2/sub3/sub4/sub5"
    },{
        "countryCode": "BH",
        "adLogo": "https://i.imgur.com/hiWd5Nz.png",
        "adImg": "https://i.imgur.com/595EqAj.jpg",
        "adVideo": "",
        "adAction": "Install",
        "adTitle": "AliExpress is a trading platform in your hands",
        "adDescription": "Millions of users find here the desired products from China at the best prices",
        "adRating": 5,
        "adLink": "http://shakesmobi.com/QUOS/sub1/sub2/sub3/sub4/sub5"
    },{
        "countryCode": "EG",
        "adLogo": "https://i.imgur.com/hiWd5Nz.png",
        "adImg": "https://i.imgur.com/595EqAj.jpg",
        "adVideo": "",
        "adAction": "Install",
        "adTitle": "AliExpress is a trading platform in your hands",
        "adDescription": "Millions of users find here the desired products from China at the best prices",
        "adRating": 5,
        "adLink": "http://shakesmobi.com/QUOS/sub1/sub2/sub3/sub4/sub5"
    },{
        "countryCode": "LB",
        "adLogo": "https://i.imgur.com/hiWd5Nz.png",
        "adImg": "https://i.imgur.com/595EqAj.jpg",
        "adVideo": "",
        "adAction": "Install",
        "adTitle": "AliExpress is a trading platform in your hands",
        "adDescription": "Millions of users find here the desired products from China at the best prices",
        "adRating": 5,
        "adLink": "http://shakesmobi.com/QUOS/sub1/sub2/sub3/sub4/sub5"
    },{
        "countryCode": "OM",
        "adLogo": "https://i.imgur.com/hiWd5Nz.png",
        "adImg": "https://i.imgur.com/595EqAj.jpg",
        "adVideo": "",
        "adAction": "Install",
        "adTitle": "AliExpress is a trading platform in your hands",
        "adDescription": "Millions of users find here the desired products from China at the best prices",
        "adRating": 5,
        "adLink": "http://shakesmobi.com/QUOS/sub1/sub2/sub3/sub4/sub5"
    },{
        "countryCode": "BR",
        "adLogo": "https://i.imgur.com/hiWd5Nz.png",
        "adImg": "https://i.imgur.com/595EqAj.jpg",
        "adVideo": "",
        "adAction": "Install",
        "adTitle": "AliExpress is a trading platform in your hands",
        "adDescription": "Millions of users find here the desired products from China at the best prices",
        "adRating": 5,
        "adLink": "http://shakesmobi.com/QUOS/sub1/sub2/sub3/sub4/sub5"
    },{
        "countryCode": "SA",
        "adLogo": "https://i.imgur.com/hiWd5Nz.png",
        "adImg": "https://i.imgur.com/595EqAj.jpg",
        "adVideo": "",
        "adAction": "Install",
        "adTitle": "AliExpress is a trading platform in your hands",
        "adDescription": "Millions of users find here the desired products from China at the best prices",
        "adRating": 5,
        "adLink": "http://shakesmobi.com/QUOS/sub1/sub2/sub3/sub4/sub5"
    },{
        "countryCode": "PH",
        "adLogo": "https://i.imgur.com/hiWd5Nz.png",
        "adImg": "https://i.imgur.com/595EqAj.jpg",
        "adVideo": "",
        "adAction": "Install",
        "adTitle": "AliExpress is a trading platform in your hands",
        "adDescription": "Millions of users find here the desired products from China at the best prices",
        "adRating": 5,
        "adLink": "http://shakesmobi.com/QUOS/sub1/sub2/sub3/sub4/sub5"
    },
    {
        "countryCode": "RU",
        "adLogo": "https://i.imgur.com/rN0EBD0.png",
        "adImg": "https://i.imgur.com/HxmLUdr.jpg",
        "adVideo": "",
        "adAction": "Установить",
        "adTitle": "War and Magic - Война близко!",
        "adDescription": "Другая волна колонистов уже на подходе. Вы готовы защитить свою колонию и альянс?",
        "adRating": 5,
        "adLink": "https://track.zorkanetwork.com/click?pid=6666&offer_id=1453"
    },
    {
        "countryCode": "RU",
        "adLogo": "https://i.imgur.com/rN0EBD0.png",
        "adImg": "https://i.imgur.com/PvcEaQc.jpg",
        "adVideo": "",
        "adAction": "Установить",
        "adTitle": "War and Magic - Война близко!",
        "adDescription": "Другая волна колонистов уже на подходе. Вы готовы защитить свою колонию и альянс?",
        "adRating": 5,
        "adLink": "https://track.zorkanetwork.com/click?pid=6666&offer_id=1453"
    },
    {
        "countryCode": "RU",
        "adLogo": "https://i.imgur.com/ijtCvfK.png",
        "adImg": "https://i.imgur.com/z13L7l0.jpg",
        "adVideo": "",
        "adAction": "Установить",
        "adTitle": "Генералы: Военные Хроники",
        "adDescription": "Масштабная онлайн-стратегия перенесет эпоху ожесточенных военных баталий и позволит почувствовать себя настоящим полководцем",
        "adRating": 5,
        "adLink": "https://track.zorkanetwork.com/click?pid=6666&offer_id=1814"
    },
    {
        "countryCode": "RU",
        "adLogo": "https://i.imgur.com/ijtCvfK.png",
        "adImg": "https://i.imgur.com/WhLdO4A.jpg",
        "adVideo": "",
        "adAction": "Установить",
        "adTitle": "Генералы: Военные Хроники",
        "adDescription": "Масштабная онлайн-стратегия перенесет эпоху ожесточенных военных баталий и позволит почувствовать себя настоящим полководцем",
        "adRating": 5,
        "adLink": "https://track.zorkanetwork.com/click?pid=6666&offer_id=1814"
    },
    {
        "countryCode": "BY",
        "adLogo": "https://i.imgur.com/ijtCvfK.png",
        "adImg": "https://i.imgur.com/z13L7l0.jpg",
        "adVideo": "",
        "adAction": "Установить",
        "adTitle": "Генералы: Военные Хроники",
        "adDescription": "Масштабная онлайн-стратегия перенесет эпоху ожесточенных военных баталий и позволит почувствовать себя настоящим полководцем",
        "adRating": 5,
        "adLink": "https://track.zorkanetwork.com/click?pid=6666&offer_id=1814"
    },
    {
        "countryCode": "BY",
        "adLogo": "https://i.imgur.com/ijtCvfK.png",
        "adImg": "https://i.imgur.com/WhLdO4A.jpg",
        "adVideo": "",
        "adAction": "Установить",
        "adTitle": "Генералы: Военные Хроники",
        "adDescription": "Масштабная онлайн-стратегия перенесет эпоху ожесточенных военных баталий и позволит почувствовать себя настоящим полководцем",
        "adRating": 5,
        "adLink": "https://track.zorkanetwork.com/click?pid=6666&offer_id=1814"
    },
    {
        "countryCode": "UA",
        "adLogo": "https://i.imgur.com/ijtCvfK.png",
        "adImg": "https://i.imgur.com/z13L7l0.jpg",
        "adVideo": "",
        "adAction": "Установить",
        "adTitle": "Генералы: Военные Хроники",
        "adDescription": "Масштабная онлайн-стратегия перенесет эпоху ожесточенных военных баталий и позволит почувствовать себя настоящим полководцем",
        "adRating": 5,
        "adLink": "https://track.zorkanetwork.com/click?pid=6666&offer_id=1814"
    },
    {
        "countryCode": "UA",
        "adLogo": "https://i.imgur.com/ijtCvfK.png",
        "adImg": "https://i.imgur.com/WhLdO4A.jpg",
        "adVideo": "",
        "adAction": "Установить",
        "adTitle": "Генералы: Военные Хроники",
        "adDescription": "Масштабная онлайн-стратегия перенесет эпоху ожесточенных военных баталий и позволит почувствовать себя настоящим полководцем",
        "adRating": 5,
        "adLink": "https://track.zorkanetwork.com/click?pid=6666&offer_id=1814"
    },
    {
        "countryCode": "RU",
        "adLogo": "https://i.imgur.com/NhoR2qE.png",
        "adImg": "https://i.imgur.com/xnDO4vl.jpg",
        "adVideo": "",
        "adAction": "Установить",
        "adTitle": "War and Order - Мир империй и воображения",
        "adDescription": "Невероятные воины ждут, чтобы начать бороться за свою империю! Летящие топоры, рев драконов, и шипение огненных шаров.",
        "adRating": 5,
        "adLink": "https://track.zorkanetwork.com/click?pid=6666&offer_id=698"
    },
    {
        "countryCode": "US",
        "adLogo": "https://i.imgur.com/tI2IYk1.jpg",
        "adImg": "https://i.imgur.com/VCEiMH0.jpg",
        "adVideo": "",
        "adAction": "Install",
        "adTitle": "Vikings: War of Clans",
        "adDescription": "Welcome to the harsh world of Vikings, where power and freedom, fear and cruelty prevail!",
        "adRating": 5,
        "adLink": "https://track.zorkanetwork.com/click?pid=6666&offer_id=488"
    },
    {
        "countryCode": "US",
        "adLogo": "https://i.imgur.com/tI2IYk1.jpg",
        "adImg": "https://i.imgur.com/HydmpPG.jpg",
        "adVideo": "",
        "adAction": "Install",
        "adTitle": "Vikings: War of Clans",
        "adDescription": "Welcome to the harsh world of Vikings, where power and freedom, fear and cruelty prevail!",
        "adRating": 5,
        "adLink": "https://track.zorkanetwork.com/click?pid=6666&offer_id=488"
    },
    {
        "countryCode": "US",
        "adLogo": "https://i.imgur.com/tI2IYk1.jpg",
        "adImg": "https://i.imgur.com/Uy1CNE6.jpg",
        "adVideo": "",
        "adAction": "Install",
        "adTitle": "Vikings: War of Clans",
        "adDescription": "Welcome to the harsh world of Vikings, where power and freedom, fear and cruelty prevail!",
        "adRating": 5,
        "adLink": "https://track.zorkanetwork.com/click?pid=6666&offer_id=488"
    },
    {
        "countryCode": "CA",
        "adLogo": "https://i.imgur.com/tI2IYk1.jpg",
        "adImg": "https://i.imgur.com/VCEiMH0.jpg",
        "adVideo": "",
        "adAction": "Install",
        "adTitle": "Vikings: War of Clans",
        "adDescription": "Welcome to the harsh world of Vikings, where power and freedom, fear and cruelty prevail!",
        "adRating": 5,
        "adLink": "https://track.zorkanetwork.com/click?pid=6666&offer_id=488"
    },
    {
        "countryCode": "CA",
        "adLogo": "https://i.imgur.com/tI2IYk1.jpg",
        "adImg": "https://i.imgur.com/HydmpPG.jpg",
        "adVideo": "",
        "adAction": "Install",
        "adTitle": "Vikings: War of Clans",
        "adDescription": "Welcome to the harsh world of Vikings, where power and freedom, fear and cruelty prevail!",
        "adRating": 5,
        "adLink": "https://track.zorkanetwork.com/click?pid=6666&offer_id=488"
    },
    {
        "countryCode": "CA",
        "adLogo": "https://i.imgur.com/tI2IYk1.jpg",
        "adImg": "https://i.imgur.com/Uy1CNE6.jpg",
        "adVideo": "",
        "adAction": "Install",
        "adTitle": "Vikings: War of Clans",
        "adDescription": "Welcome to the harsh world of Vikings, where power and freedom, fear and cruelty prevail!",
        "adRating": 5,
        "adLink": "https://track.zorkanetwork.com/click?pid=6666&offer_id=488"
    },
    {
        "countryCode": "AU",
        "adLogo": "https://i.imgur.com/tI2IYk1.jpg",
        "adImg": "https://i.imgur.com/VCEiMH0.jpg",
        "adVideo": "",
        "adAction": "Install",
        "adTitle": "Vikings: War of Clans",
        "adDescription": "Welcome to the harsh world of Vikings, where power and freedom, fear and cruelty prevail!",
        "adRating": 5,
        "adLink": "https://track.zorkanetwork.com/click?pid=6666&offer_id=488"
    },
    {
        "countryCode": "AU",
        "adLogo": "https://i.imgur.com/tI2IYk1.jpg",
        "adImg": "https://i.imgur.com/HydmpPG.jpg",
        "adVideo": "",
        "adAction": "Install",
        "adTitle": "Vikings: War of Clans",
        "adDescription": "Welcome to the harsh world of Vikings, where power and freedom, fear and cruelty prevail!",
        "adRating": 5,
        "adLink": "https://track.zorkanetwork.com/click?pid=6666&offer_id=488"
    },
    {
        "countryCode": "AU",
        "adLogo": "https://i.imgur.com/tI2IYk1.jpg",
        "adImg": "https://i.imgur.com/Uy1CNE6.jpg",
        "adVideo": "",
        "adAction": "Install",
        "adTitle": "Vikings: War of Clans",
        "adDescription": "Welcome to the harsh world of Vikings, where power and freedom, fear and cruelty prevail!",
        "adRating": 5,
        "adLink": "https://track.zorkanetwork.com/click?pid=6666&offer_id=488"
    }
]
